pymesh/__init__.py
pymesh/colormap/__init__.py
pymesh/colormap/colormap.py
pymesh/interp3d/__init__.py
pymesh/interp3d/interp_color.py
pymesh/interp3d/rotate.py
pymesh/iso_surf/__init__.py
pymesh/iso_surf/iso_surf.py
pymesh/iso_surf/marching_cubes.py
pymesh/mesh/__init__.py
pymesh/mesh/mesh.py
pymesh/show/__init__.py
pymesh/show/mlab_plot.py
pymesh/show/plt_plot.py
pymesh3d-0.0.17.dist-info/LICENSE
pymesh3d-0.0.17.dist-info/METADATA
pymesh3d-0.0.17.dist-info/WHEEL
pymesh3d-0.0.17.dist-info/top_level.txt
pymesh3d-0.0.17.dist-info/RECORD
