Metadata-Version: 2.1
Name: pymesh3d
Version: 0.0.17
Summary: mesh extract and render by python
Home-page: https://github.com/zhazhajust/pymesh.git
Author: Cai Jie
Author-email: jiecai@stu.pku.edu.cn
Classifier: Programming Language :: Python :: 3
Classifier: License :: OSI Approved :: MIT License
Classifier: Operating System :: OS Independent
Requires-Python: >=3.6
License-File: LICENSE
Requires-Dist: numpy
Requires-Dist: numba
Requires-Dist: scikit-image
Requires-Dist: trimesh
Requires-Dist: rtree
Requires-Dist: matplotlib
